{"id":168,"date":"2020-08-10T09:06:03","date_gmt":"2020-08-10T09:06:03","guid":{"rendered":"https:\/\/demo2.pavothemes.com\/freshio\/product\/enormous-marble-shoes\/"},"modified":"2020-08-14T06:54:30","modified_gmt":"2020-08-14T06:54:30","slug":"enormous-marble-shoes","status":"publish","type":"product","link":"https:\/\/demo2.pavothemes.com\/freshio\/product\/enormous-marble-shoes\/","title":{"rendered":"Enormous Marble Shoes"},"content":{"rendered":"<p>Illum praesentium magnam rerum enim. Eveniet velit suscipit omnis. Adipisci ab ut distinctio qui qui. Nesciunt repellendus optio vitae quo.<\/p>\n<p>Odit perferendis minus voluptates. Atque eligendi voluptate autem libero voluptatem dolores dolorum. Maxime voluptas quia dicta qui. Eum eius placeat nam atque. Minima labore suscipit blanditiis aut voluptas cupiditate.<\/p>\n<p>Modi aliquam vitae voluptatibus voluptates reprehenderit suscipit minima. Aut impedit at nemo quibusdam repudiandae libero delectus enim.<\/p>\n<p>Distinctio labore commodi non rerum omnis. Rerum nam similique omnis qui veritatis. Aliquam velit molestiae ea mollitia nam. Sint soluta velit nobis fuga. Et quia eveniet voluptas impedit dolore nemo pariatur.<\/p>\n<p>Unde quia commodi commodi repellendus aliquam sit quaerat. Quidem vel rem sed nihil maxime cupiditate. Molestias dolorem ut ducimus explicabo. Dolores vero officiis quaerat eius perspiciatis.<\/p>\n","protected":false},"excerpt":{"rendered":"<p>Odio voluptas iusto et qui numquam aut quasi magni. Molestiae quia quo consequatur optio et. Magnam vel consectetur id iusto a esse.<\/p>\n","protected":false},"featured_media":293,"comment_status":"closed","ping_status":"closed","template":"","meta":[],"_links":{"self":[{"href":"https:\/\/demo2.pavothemes.com\/freshio\/wp-json\/wp\/v2\/product\/168"}],"collection":[{"href":"https:\/\/demo2.pavothemes.com\/freshio\/wp-json\/wp\/v2\/product"}],"about":[{"href":"https:\/\/demo2.pavothemes.com\/freshio\/wp-json\/wp\/v2\/types\/product"}],"replies":[{"embeddable":true,"href":"https:\/\/demo2.pavothemes.com\/freshio\/wp-json\/wp\/v2\/comments?post=168"}],"wp:featuredmedia":[{"embeddable":true,"href":"https:\/\/demo2.pavothemes.com\/freshio\/wp-json\/wp\/v2\/media\/293"}],"wp:attachment":[{"href":"https:\/\/demo2.pavothemes.com\/freshio\/wp-json\/wp\/v2\/media?parent=168"}],"curies":[{"name":"wp","href":"https:\/\/api.w.org\/{rel}","templated":true}]}}